cli/__init__.py
cli/nbconv_cli.py
cli/nbdeck_cli.py
cli/nbexec_cli.py
cli/nbless_cli.py
cli/nbraze_cli.py
cli/nbuild_cli.py
nbless/__init__.py
nbless/nbconv.py
nbless/nbdeck.py
nbless/nbexec.py
nbless/nbless.py
nbless/nbraze.py
nbless/nbuild.py
nbless-0.2.38.dist-info/LICENSE.txt
nbless-0.2.38.dist-info/METADATA
nbless-0.2.38.dist-info/WHEEL
nbless-0.2.38.dist-info/entry_points.txt
nbless-0.2.38.dist-info/top_level.txt
nbless-0.2.38.dist-info/RECORD
