Metadata-Version: 2.1
Name: nbless
Version: 0.2.38
Summary: Construct, deconstruct, convert, and run Jupyter notebooks.
Home-page: https://github.com/marskar/nbless
Author: Martin Skarzynski
Author-email: marskar@gmail.com
License: UNKNOWN
Platform: UNKNOWN
Classifier: Development Status :: 4 - Beta
Classifier: Intended Audience :: Developers
Classifier: License :: OSI Approved :: MIT License
Classifier: Natural Language :: English
Classifier: Programming Language :: Python :: 3.6
Classifier: Programming Language :: Python :: 3.7
Requires-Python: >=3.6
Requires-Dist: click
Requires-Dist: jupyter
Requires-Dist: pypandoc
